rivertils/__init__.py
rivertils/dump.py
rivertils/lists.py
rivertils/profile.py
rivertils/rivertils.py
rivertils/services.py
rivertils-0.1.13.dist-info/WHEEL
rivertils-0.1.13.dist-info/METADATA
rivertils-0.1.13.dist-info/RECORD
