Metadata-Version: 2.1
Name: rivertils
Version: 0.1.13
Summary: utilities commonly used by rivers cuomo
Author: Rivers Cuomo
Author-email: riverscuomo@users.noreply.github.com
Requires-Python: >=3.8,<4.0
Classifier: Programming Language :: Python :: 3
Classifier: Programming Language :: Python :: 3.8
Classifier: Programming Language :: Python :: 3.9
Classifier: Programming Language :: Python :: 3.10
Classifier: Programming Language :: Python :: 3.11
Requires-Dist: google-cloud-translate (==3.9.0)
